MANIFEST.in
README.rst
setup.py
django_elasticache/__init__.py
django_elasticache/cluster_utils.py
django_elasticache/memcached.py
django_elasticache.egg-info/PKG-INFO
django_elasticache.egg-info/SOURCES.txt
django_elasticache.egg-info/dependency_links.txt
django_elasticache.egg-info/requires.txt
django_elasticache.egg-info/top_level.txt