Metadata-Version: 1.1
Name: django-elasticache
Version: 0.0.3
Summary: Django cache backend for Amazon ElastiCache (memcached)
Home-page: http://github.com/gusdan/django-elasticache
Author: Danil Gusev
Author-email: danil.gusev@gmail.com
License: MIT
Keywords: elasticache amazon cache pylibmc memcached aws
Platform: any
Classifier: Development Status :: 4 - Beta
Classifier: Environment :: Web Environment
Classifier: Environment :: Web Environment :: Mozilla
Classifier: Framework :: Django
Classifier: Intended Audience :: Developers
Classifier: License :: OSI Approved :: BSD License
Classifier: Operating System :: OS Independent
Classifier: Programming Language :: Python
Classifier: Topic :: Software Development :: Libraries :: Python Modules
